aes3tool/__init__.py
aes3tool/__main__.py
aes3tool/bitstream.py
aes3tool/buffer.py
aes3tool/config.py
aes3tool/const.py
aes3tool/data.py
aes3tool/network.py
aes3tool/output.py
aes3tool/processor.py
aes3tool/receiver.py
aes3tool/stats.py
aes3tool/transmitter.py
aes3tool-1.1.0.dist-info/METADATA
aes3tool-1.1.0.dist-info/WHEEL
aes3tool-1.1.0.dist-info/entry_points.txt
aes3tool-1.1.0.dist-info/licenses/LICENSE
aes3tool-1.1.0.dist-info/RECORD
