Metadata-Version: 2.3
Name: aes3tool
Version: 1.1.0
Summary: SMPTE 2110-3x AES3 PCM testing toolkit
Project-URL: Homepage, https://github.com/opdenkamp/
Project-URL: Documentation, https://github.com/opdenkamp/aes3tool
Project-URL: Repository, https://github.com/opdenkamp/aes3tool.git
Project-URL: Bug Tracker, https://github.com/opdenkamp/aes3tool/issues
Author-email: Lars Op den Kamp <lars@opdenkamp.eu>
Maintainer-email: Lars Op den Kamp <lars@opdenkamp.eu>
License: Copyright 2024 Lars Op den Kamp <lars@opdenkamp.eu>
Keywords: 2110-30,2110-31,aes3,smpte
Classifier: Development Status :: 3 - Alpha
Classifier: Programming Language :: Python
Classifier: Topic :: System :: Networking :: Monitoring
Requires-Python: >=3.11
Requires-Dist: numpy
Requires-Dist: pyaudio
Requires-Dist: pydub>=0.25.1
Requires-Dist: resampy>=0.4.3
